qwed_sdk/README.md
qwed_sdk/__init__.py
qwed_sdk/cache.py
qwed_sdk/cli.py
qwed_sdk/client.py
qwed_sdk/crewai.py
qwed_sdk/langchain.py
qwed_sdk/llamaindex.py
qwed_sdk/models.py
qwed_sdk/pii_detector.py
qwed_sdk/qwed_local.py
qwed_sdk/integrations/__init__.py
qwed_sdk/integrations/langchain.py
qwed_new/__init__.py
qwed_new/config.py
qwed_new/api/__init__.py
qwed_new/api/badges.py
qwed_new/api/main.py
qwed_new/auth/__init__.py
qwed_new/auth/audit_database.py
qwed_new/auth/audit_models.py
qwed_new/auth/audit_routes.py
qwed_new/auth/database.py
qwed_new/auth/middleware.py
qwed_new/auth/models.py
qwed_new/auth/routes.py
qwed_new/auth/security.py
qwed_new/core/__init__.py
qwed_new/core/ablation_tracker.py
qwed_new/core/agent_models.py
qwed_new/core/agent_registry.py
qwed_new/core/agent_service.py
qwed_new/core/alerting.py
qwed_new/core/attestation.py
qwed_new/core/audit_logger.py
qwed_new/core/batch.py
qwed_new/core/cache.py
qwed_new/core/code_executor.py
qwed_new/core/code_verifier.py
qwed_new/core/compliance_exporter.py
qwed_new/core/consensus_verifier.py
qwed_new/core/control_plane.py
qwed_new/core/database.py
qwed_new/core/dsl_logic_verifier.py
qwed_new/core/fact_verifier.py
qwed_new/core/image_verifier.py
qwed_new/core/key_rotation.py
qwed_new/core/logic_verifier.py
qwed_new/core/models.py
qwed_new/core/money.py
qwed_new/core/observability.py
qwed_new/core/output_sanitizer.py
qwed_new/core/password_context_helper.py
qwed_new/core/policy.py
qwed_new/core/rate_limiter.py
qwed_new/core/rbac.py
qwed_new/core/reasoning_verifier.py
qwed_new/core/redis_config.py
qwed_new/core/router.py
qwed_new/core/safe_evaluator.py
qwed_new/core/sanitizer.py
qwed_new/core/schemas.py
qwed_new/core/secure_code_executor.py
qwed_new/core/security.py
qwed_new/core/sql_verifier.py
qwed_new/core/stats_verifier.py
qwed_new/core/symbolic_verifier.py
qwed_new/core/telemetry.py
qwed_new/core/tenant_context.py
qwed_new/core/threat_detector.py
qwed_new/core/tool_approval.py
qwed_new/core/translator.py
qwed-2.3.0.dist-info/METADATA
qwed-2.3.0.dist-info/WHEEL
qwed-2.3.0.dist-info/entry_points.txt
qwed-2.3.0.dist-info/licenses/LICENSE
qwed-2.3.0.dist-info/RECORD
