Metadata-Version: 2.4
Name: qwed
Version: 2.3.0
Summary: The Deterministic Verification Protocol for AI - 8 verification engines for math, logic, code, SQL, facts, images, and more.
Project-URL: Homepage, https://qwedai.com
Project-URL: Documentation, https://docs.qwedai.com
Project-URL: Repository, https://github.com/QWED-AI/qwed-verification
Project-URL: Changelog, https://github.com/QWED-AI/qwed-verification/blob/main/CHANGELOG.md
Author-email: QWED Team <rahul@qwedai.com>
License: Apache-2.0
License-File: LICENSE
Keywords: ai,code-security,deterministic,fact-checking,llm,logic,math,sql-validation,symbolic,verification
Classifier: Development Status :: 4 - Beta
Classifier: Intended Audience :: Developers
Classifier: License :: OSI Approved :: Apache Software License
Classifier: Operating System :: OS Independent
Classifier: Programming Language :: Python :: 3
Classifier: Programming Language :: Python :: 3.10
Classifier: Programming Language :: Python :: 3.11
Classifier: Programming Language :: Python :: 3.12
Classifier: Topic :: Scientific/Engineering :: Artificial Intelligence
Classifier: Topic :: Security
Classifier: Topic :: Software Development :: Quality Assurance
Requires-Python: >=3.10
Requires-Dist: anthropic>=0.1.0
Requires-Dist: bcrypt>=4.0.1
Requires-Dist: click>=8.1.0
Requires-Dist: fastapi>=0.100.0
Requires-Dist: httpx>=0.24.0
Requires-Dist: networkx>=3.0
Requires-Dist: numpy>=1.24.0
Requires-Dist: openai>=1.0.0
Requires-Dist: pandas>=2.0.0
Requires-Dist: passlib[bcrypt]>=1.7.4
Requires-Dist: pydantic[email]>=2.0.0
Requires-Dist: pyjwt>=2.8.0
Requires-Dist: python-dotenv>=1.0.0
Requires-Dist: python-multipart>=0.0.6
Requires-Dist: requests>=2.31.0
Requires-Dist: scipy>=1.10.0
Requires-Dist: sqlglot>=20.0.0
Requires-Dist: sqlmodel>=0.0.14
Requires-Dist: sympy>=1.12
Requires-Dist: uvicorn>=0.20.0
Requires-Dist: z3-solver>=4.12.0
Provides-Extra: dev
Requires-Dist: docker>=7.0.0; extra == 'dev'
Requires-Dist: freezegun>=1.4.0; extra == 'dev'
Requires-Dist: matplotlib>=3.7.0; extra == 'dev'
Requires-Dist: pytest-asyncio>=0.21.0; extra == 'dev'
Requires-Dist: pytest-timeout>=2.3.1; extra == 'dev'
Requires-Dist: pytest-xdist>=3.3.0; extra == 'dev'
Requires-Dist: pytest>=7.0.0; extra == 'dev'
Requires-Dist: pyyaml>=6.0.1; extra == 'dev'
Provides-Extra: server
Requires-Dist: opentelemetry-api>=1.20.0; extra == 'server'
Requires-Dist: opentelemetry-exporter-otlp>=1.20.0; extra == 'server'
Requires-Dist: opentelemetry-instrumentation-fastapi>=0.41b0; extra == 'server'
Requires-Dist: opentelemetry-instrumentation-requests>=0.41b0; extra == 'server'
Requires-Dist: opentelemetry-sdk>=1.20.0; extra == 'server'
Requires-Dist: prometheus-client>=0.19.0; extra == 'server'
Requires-Dist: psycopg2-binary>=2.9.9; extra == 'server'
Requires-Dist: redis>=5.0.0; extra == 'server'
Provides-Extra: symbolic
Requires-Dist: crosshair-tool>=0.0.100; extra == 'symbolic'
